lobbyboy/__init__.py
lobbyboy/conf/lobbyboy_config.toml
lobbyboy/config.py
lobbyboy/contrib/__init__.py
lobbyboy/contrib/provider/__init__.py
lobbyboy/contrib/provider/digitalocean.py
lobbyboy/contrib/provider/footloose.py
lobbyboy/contrib/provider/ignite.py
lobbyboy/contrib/provider/linode.py
lobbyboy/contrib/provider/vagrant.py
lobbyboy/exceptions.py
lobbyboy/main.py
lobbyboy/provider.py
lobbyboy/scripts.py
lobbyboy/server.py
lobbyboy/server_killer.py
lobbyboy/socket_handle.py
lobbyboy/utils.py
lobbyboy-0.4.0.dist-info/entry_points.txt
lobbyboy-0.4.0.dist-info/WHEEL
lobbyboy-0.4.0.dist-info/METADATA
lobbyboy-0.4.0.dist-info/RECORD
