Metadata-Version: 2.1
Name: lobbyboy
Version: 0.4.0
Summary: Give me a server.
License: GNU
Author: laixintao
Author-email: laixintaoo@gmail.com
Requires-Python: >=3.7,<4.0
Classifier: License :: Other/Proprietary License
Classifier: Programming Language :: Python :: 3
Classifier: Programming Language :: Python :: 3.10
Classifier: Programming Language :: Python :: 3.7
Classifier: Programming Language :: Python :: 3.8
Classifier: Programming Language :: Python :: 3.9
Requires-Dist: linode-api4 (>=5.2.1,<6.0.0)
Requires-Dist: paramiko[gssapi] (>=2.8.0,<3.0.0)
Requires-Dist: python-digitalocean (>=1.17.0,<2.0.0)
Requires-Dist: toml (>=0.10.2,<0.11.0)
